cubicweb_workcase/__init__.py
cubicweb_workcase/__pkginfo__.py
cubicweb_workcase/entities.py
cubicweb_workcase/schema.py
cubicweb_workcase/sobjects.py
cubicweb_workcase/uiprops.py
cubicweb_workcase/views.py
cubicweb_workcase/data/icon_workcase.gif
cubicweb_workcase/i18n/en.po
cubicweb_workcase/i18n/fr.po
cubicweb_workcase/migration/0.5.1_Any.py
cubicweb_workcase/migration/postcreate.py
cubicweb_workcase/migration/postreinitialize.py
cubicweb_workcase/wdoc/ChangeLog_en
cubicweb_workcase/wdoc/ChangeLog_fr
cubicweb_workcase-1.1.0.dist-info/METADATA
cubicweb_workcase-1.1.0.dist-info/WHEEL
cubicweb_workcase-1.1.0.dist-info/entry_points.txt
cubicweb_workcase-1.1.0.dist-info/top_level.txt
cubicweb_workcase-1.1.0.dist-info/RECORD
